flux0_server/__init__.py
flux0_server/app.py
flux0_server/container_factory.py
flux0_server/main.py
flux0_server/settings.py
flux0_server/version.py
flux0_server-0.1.0b4.data/data/flux0-chat/static/index.html
flux0_server-0.1.0b4.data/data/flux0-chat/static/assets/_agentId-CERAas0y.js
flux0_server-0.1.0b4.data/data/flux0-chat/static/assets/_agentId-CRKUCv0_.js
flux0_server-0.1.0b4.data/data/flux0-chat/static/assets/_layout-De5ZKK5G.js
flux0_server-0.1.0b4.data/data/flux0-chat/static/assets/_sessionId-DnCQsqNc.js
flux0_server-0.1.0b4.data/data/flux0-chat/static/assets/_sessionId-tIvosvcZ.js
flux0_server-0.1.0b4.data/data/flux0-chat/static/assets/chat-CdJpwiky.js
flux0_server-0.1.0b4.data/data/flux0-chat/static/assets/chat-header-KHbMuBui.js
flux0_server-0.1.0b4.data/data/flux0-chat/static/assets/index-B3TsnAiv.js
flux0_server-0.1.0b4.data/data/flux0-chat/static/assets/index-C5pqq8p4.js
flux0_server-0.1.0b4.data/data/flux0-chat/static/assets/index-CERtTpnO.css
flux0_server-0.1.0b4.data/data/flux0-chat/static/assets/index-CLxOGfT0.js
flux0_server-0.1.0b4.data/data/flux0-chat/static/assets/index-DDAypnch.js
flux0_server-0.1.0b4.data/data/flux0-chat/static/assets/sidebar-toggle-D8wRPeaZ.js
flux0_server-0.1.0b4.dist-info/METADATA
flux0_server-0.1.0b4.dist-info/WHEEL
flux0_server-0.1.0b4.dist-info/RECORD
