Metadata-Version: 2.4
Name: flux0-server
Version: 0.1.0b4
Requires-Python: >=3.13
Requires-Dist: flux0-api==0.1.0-beta.3
Requires-Dist: pydantic-settings>=2.8.1
Requires-Dist: toml>=0.10.2
Requires-Dist: uvicorn>=0.34.0
